apphelpers/__init__.py
apphelpers/context.py
apphelpers/errors.py
apphelpers/sessions.py
apphelpers/db/__init__.py
apphelpers/db/peewee.py
apphelpers/rest/__init__.py
apphelpers/rest/fastapi.py
apphelpers/rest/flask.py
apphelpers/rest/flaskutils.py
apphelpers/rest/hug.py
apphelpers/rest/starlette.py
apphelpers/utilities/__init__.py
apphelpers/utilities/email.py
tests/app/__init__.py
tests/app/endpoints.py
tests/app/models.py
apphelpers-0.12.2.dist-info/AUTHORS.rst
apphelpers-0.12.2.dist-info/LICENSE
apphelpers-0.12.2.dist-info/METADATA
apphelpers-0.12.2.dist-info/WHEEL
apphelpers-0.12.2.dist-info/top_level.txt
apphelpers-0.12.2.dist-info/RECORD
