Metadata-Version: 2.1
Name: apphelpers
Version: 0.12.2
Summary: Common helper libraries for Python Apps
Home-page: https://github.com/scrolltech/apphelpers
Author: Scroll Tech
Author-email: tech@scroll.in
License: MIT license
Keywords: apphelpers
Platform: UNKNOWN
Classifier: Development Status :: 2 - Pre-Alpha
Classifier: Intended Audience :: Developers
Classifier: License :: OSI Approved :: MIT License
Classifier: Natural Language :: English
Classifier: Programming Language :: Python :: 3.6
Classifier: Programming Language :: Python :: 3.7
